{"series_tiempo": [{"mes": 0, "trans_activos": 87.7, "cajas_activos": 220.1, "n_activos": 173347, "trans_churn": 18.1, "cajas_churn": 60.1, "n_churn": 79}, {"mes": 1, "trans_activos": 27.6, "cajas_activos": 71.0, "n_activos": 453, "trans_churn": 13.3, "cajas_churn": 26.1, "n_churn": 600}, {"mes": 2, "trans_activos": 11.1, "cajas_activos": 28.8, "n_activos": 821, "trans_churn": 3.4, "cajas_churn": 5.5, "n_churn": 124}, {"mes": 3, "trans_activos": 34.3, "cajas_activos": 118.0, "n_activos": 215, "trans_churn": 3.2, "cajas_churn": 5.8, "n_churn": 30}, {"mes": 4, "trans_activos": 50.0, "cajas_activos": 134.3, "n_activos": 225, "trans_churn": 2.8, "cajas_churn": 6.7, "n_churn": 34}, {"mes": 5, "trans_activos": 52.7, "cajas_activos": 141.8, "n_activos": 145, "trans_churn": 3.0, "cajas_churn": 6.0, "n_churn": 15}, {"mes": 6, "trans_activos": 59.4, "cajas_activos": 170.4, "n_activos": 151, "trans_churn": 1.0, "cajas_churn": 0.2, "n_churn": 1}, {"mes": 7, "trans_activos": 70.7, "cajas_activos": 196.7, "n_activos": 125, "trans_churn": 1.0, "cajas_churn": 2.6, "n_churn": 2}, {"mes": 8, "trans_activos": 57.5, "cajas_activos": 139.5, "n_activos": 128, "trans_churn": 2.0, "cajas_churn": 2.9, "n_churn": 2}, {"mes": 9, "trans_activos": 69.6, "cajas_activos": 190.4, "n_activos": 121, "trans_churn": 1.0, "cajas_churn": 0.6, "n_churn": 1}, {"mes": 10, "trans_activos": 66.2, "cajas_activos": 176.7, "n_activos": 96, "trans_churn": 2.0, "cajas_churn": 1.3, "n_churn": 1}, {"mes": 11, "trans_activos": 58.3, "cajas_activos": 155.8, "n_activos": 89}, {"mes": 12, "trans_activos": 59.5, "cajas_activos": 157.0, "n_activos": 88, "trans_churn": 1.0, "cajas_churn": 1.1, "n_churn": 1}, {"mes": 13, "trans_activos": 73.7, "cajas_activos": 211.6, "n_activos": 74, "trans_churn": 6.0, "cajas_churn": 34.8, "n_churn": 1}, {"mes": 14, "trans_activos": 63.6, "cajas_activos": 212.0, "n_activos": 65}, {"mes": 15, "trans_activos": 63.6, "cajas_activos": 175.5, "n_activos": 64}, {"mes": 16, "trans_activos": 83.2, "cajas_activos": 234.1, "n_activos": 94, "trans_churn": 1.0, "cajas_churn": 0.6, "n_churn": 1}, {"mes": 17, "trans_activos": 70.7, "cajas_activos": 191.7, "n_activos": 82}, {"mes": 18, "trans_activos": 72.9, "cajas_activos": 193.8, "n_activos": 65}, {"mes": 19, "trans_activos": 58.2, "cajas_activos": 152.7, "n_activos": 88}, {"mes": 20, "trans_activos": 78.9, "cajas_activos": 204.4, "n_activos": 65, "trans_churn": 1.0, "cajas_churn": 3.5, "n_churn": 1}, {"mes": 21, "trans_activos": 89.2, "cajas_activos": 237.1, "n_activos": 87}, {"mes": 22, "trans_activos": 85.3, "cajas_activos": 262.2, "n_activos": 57}, {"mes": 23, "trans_activos": 84.5, "cajas_activos": 249.7, "n_activos": 49}, {"mes": 24, "trans_activos": 89.6, "cajas_activos": 250.8, "n_activos": 74}], "volatilidad": [{"nivel_riesgo": "Alto", "churn_real": 1, "var_trans": 0.0, "var_cajas": 0.0, "trans": 6.6563088512241055, "cajas": 14.7602031460452, "n": 1062}, {"nivel_riesgo": "Bajo", "churn_real": 0, "var_trans": 0.0, "var_cajas": 0.0, "trans": 82.83242667748232, "cajas": 209.8753307600875, "n": 197245}, {"nivel_riesgo": "Medio", "churn_real": 0, "var_trans": 0.0, "var_cajas": 0.0, "trans": 38.4111328125, "cajas": 91.76561114726563, "n": 1024}, {"nivel_riesgo": "Medio", "churn_real": 1, "var_trans": 0.0, "var_cajas": 0.0, "trans": 7.423986486486487, "cajas": 18.347033217060815, "n": 592}]}